main.py
commands/auth.py
commands/control.py
commands/live_monitor.py
commands/monitor.py
commands/operations.py
core/info.py
selfops-0.1.5.dist-info/licenses/LICENSE
utils/file_utility.py
utils/middleware.py
selfops-0.1.5.dist-info/METADATA
selfops-0.1.5.dist-info/WHEEL
selfops-0.1.5.dist-info/entry_points.txt
selfops-0.1.5.dist-info/top_level.txt
selfops-0.1.5.dist-info/RECORD
